{
"type": "FeatureCollection",
"name": "Bandara",
"crs": { "type": "name", "properties": { "name": "urn:ogc:def:crs:OGC:1.3:CRS84" } },
"features": [
{ "type": "Feature", "properties": { "Bandara": "Banyuwangi International Airport (Bandar Udara Bli" }, "geometry": { "type": "Point", "coordinates": [ 114.341, -8.312047 ] } }
]
}
